py_rust_encode_varint-0.3.13.dist-info/METADATA
py_rust_encode_varint-0.3.13.dist-info/WHEEL
py_rust_encode_varint/__init__.py
py_rust_encode_varint/__init__.pyi
py_rust_encode_varint/py.typed
py_rust_encode_varint/py_rust_encode_varint.cpython-314t-x86_64-linux-gnu.so
py_rust_encode_varint-0.3.13.dist-info/RECORD
