Metadata-Version: 2.4
Name: py_rust_encode_varint
Version: 0.3.13
Summary: Encode varint using Protocol Buffers format (same as Python implementation)
Requires-Python: >=3.14
